<?xml version="1.0" encoding="UTF-8" standalone="yes"?><wantedDtl><resultCode>0</resultCode><resultMessage>SUCCESS</resultMessage><servId>WLF00004757</servId><servNm>부안군여성청소년생리용품지원사업</servNm><enfcBgngYmd>20220101</enfcBgngYmd><enfcEndYmd>99991231</enfcEndYmd><bizChrDeptNm>전북특별자치도 부안군 행정복지국 교육청소년과</bizChrDeptNm><ctpvNm>전북특별자치도</ctpvNm><sggNm>부안군</sggNm><servDgst>청소년복지지원법 제5조제3항에 따라 여성청소년의 건강증진과 복지향상 기여</servDgst><lifeNmArray>청소년</lifeNmArray><intrsThemaNmArray>입양·위탁, 서민금융</intrsThemaNmArray><sprtCycNm>분기</sprtCycNm><srvPvsnNm>지역화폐</srvPvsnNm><aplyMtdNm>방문</aplyMtdNm><sprtTrgtCn>부안군 관내 여성청소년(11세~18세 이하)
※동일 내용 타사업 중복 불가</sprtTrgtCn><slctCritCn>부안군에 주민등록을 두고 있는 여성 청소년(11~18세)
※동일 내용 타사업 중복 불가</slctCritCn><alwServCn>여성청소년보건위생물품 구입 전용 전자바우처 지급</alwServCn><aplyMtdCn>신분증 지참 후 방문, 신청서 작성</aplyMtdCn><inqNum>2799</inqNum><lastModYmd>20260704</lastModYmd><inqplCtadrList><wlfareInfoDtlCd>010</wlfareInfoDtlCd><wlfareInfoReldCn>580-4402</wlfareInfoReldCn><wlfareInfoReldNm>부안군청 교육청소년과 여성청소년팀</wlfareInfoReldNm></inqplCtadrList><baslawList><wlfareInfoDtlCd>030</wlfareInfoDtlCd><wlfareInfoReldNm>부안군 여성청소년생리용품 지원 조례</wlfareInfoReldNm></baslawList><basfrmList><wlfareInfoDtlCd>040</wlfareInfoDtlCd><wlfareInfoReldCn>https://www.bokjiro.go.kr/ssis-tbu/CmmFileUtil/siteQnaInfoDownload.do?atcflId=20250731UUWBM1723430148959100&amp;atcflSn=1</wlfareInfoReldCn><wlfareInfoReldNm>부안군 여성청소년 생리용품 지원 조례.pdf</wlfareInfoReldNm></basfrmList></wantedDtl>