<?xml version="1.0" encoding="UTF-8" standalone="yes"?><wantedDtl><resultCode>0</resultCode><resultMessage>SUCCESS</resultMessage><servId>WLF00005625</servId><servNm>미등록경로당 지원 사업</servNm><enfcBgngYmd>20240101</enfcBgngYmd><enfcEndYmd>99991231</enfcEndYmd><bizChrDeptNm>경상북도 문경시 행정복지국 시니어장애인과</bizChrDeptNm><ctpvNm>경상북도</ctpvNm><sggNm>문경시</sggNm><servDgst>어르신들의 복지 증진을 위해 경로당으로 등록하기 위한 시설기준을 충족하지 못하여 지원에서 소외당하고 있는 미등록 경로당 어르신들의 복지를 위하여 최소한의 지원 근거를 마련하여 실질적으로 형평성 있는 복지혜택을 받을 수 있도록 하기 위함</servDgst><lifeNmArray>노년</lifeNmArray><intrsThemaNmArray>서민금융</intrsThemaNmArray><sprtCycNm>반기</sprtCycNm><srvPvsnNm>현금지급</srvPvsnNm><aplyMtdNm>방문</aplyMtdNm><sprtTrgtCn>2023년 12월 31일 이전 미등록경로당으로 운영중인 시설</sprtTrgtCn><slctCritCn>2023년 12월 31일 이전 운영중인 미등록경로당</slctCritCn><alwServCn>미등록경로당 

냉낭비 연 300,000(7월분 150,000원, 8월분 150,000원)
난방비 연 1,700,000원(1-3월, 11-12월분   월 340,000원)
부식비 연 1,200,000원
양곡비 연 140,000원</alwServCn><aplyMtdCn>미등록경로당으로 등록을 원하는 시설은 읍면동 행정복지센터 신청 후 
시에서 해당여부 처리</aplyMtdCn><inqNum>1001</inqNum><lastModYmd>20250815</lastModYmd><inqplCtadrList><wlfareInfoDtlCd>010</wlfareInfoDtlCd><wlfareInfoReldCn>054-550-6376</wlfareInfoReldCn><wlfareInfoReldNm>문경시 노인장애인복지과</wlfareInfoReldNm></inqplCtadrList><baslawList><wlfareInfoDtlCd>030</wlfareInfoDtlCd><wlfareInfoReldNm>문경시 경로당 지원에 관한 조례</wlfareInfoReldNm></baslawList><basfrmList><wlfareInfoDtlCd>040</wlfareInfoDtlCd><wlfareInfoReldCn>https://www.bokjiro.go.kr/ssis-tbu/CmmFileUtil/siteQnaInfoDownload.do?atcflId=20240703UUWBM1041080092340252&amp;atcflSn=1</wlfareInfoReldCn><wlfareInfoReldNm>문경시 경로당 지원에 관한 조례.pdf</wlfareInfoReldNm></basfrmList></wantedDtl>