<?xml version="1.0" encoding="UTF-8" standalone="yes"?><wantedDtl><resultCode>0</resultCode><resultMessage>SUCCESS</resultMessage><servId>WLF00006527</servId><servNm>저장강박 의심 위기가구 지원사업</servNm><enfcBgngYmd>20210101</enfcBgngYmd><enfcEndYmd>99991231</enfcEndYmd><bizChrDeptNm>전북특별자치도 군산시 복지교육국 복지정책과</bizChrDeptNm><ctpvNm>전북특별자치도</ctpvNm><sggNm>군산시</sggNm><servDgst>❍ 사업기간: 연중
❍ 사 업 비: 10백만원(시 100%). 
❍ 사업대상: 군산시에 주민등록을 두고 거주하는 주민 중에서 저장강박 의심가구로 인정하는 가구 * 주거환경개선 동의 시 개입
❍ 사업내용: 저장강박 세대 집안청소 및 소독, 상담치료 연계 등</servDgst><sprtCycNm>년</sprtCycNm><srvPvsnNm>기타</srvPvsnNm><aplyMtdNm>방문, 전화</aplyMtdNm><sprtTrgtCn>군산시에 주민등록을 두고 거주하는 주민 중에서 저장강박 의심가구로 인정하는 가구 
* 주거환경개선 동의 시 개입</sprtTrgtCn><slctCritCn>군산시에 주민등록을 두고 거주하는 주민 중에서 저장강박 의심가구로 인정하는 가구  * 주거환경개선 동의 시 개입
▪집안에 쓰레기 등을 저장하여 악취, 벌레 서식 등으로 개인위생 문제 가구
▪폐지, 재활용품을 적재하여 화재위험 등에 노출, 이웃주민들에게 불만 야기 가구
▪사회적 및 대인관계 문제로 가족, 친구, 이웃들과의 관계 단절된 가구</slctCritCn><alwServCn>주거환경개선</alwServCn><aplyMtdCn>읍면동 및 복지정책과 희망복지지원계 문의 및 신청</aplyMtdCn><inqNum>62</inqNum><lastModYmd>20260704</lastModYmd><inqplCtadrList><wlfareInfoDtlCd>010</wlfareInfoDtlCd><wlfareInfoReldCn>063-454-3082</wlfareInfoReldCn><wlfareInfoReldNm>군산시청 복지정책과 희망복지지원계</wlfareInfoReldNm></inqplCtadrList><baslawList><wlfareInfoDtlCd>030</wlfareInfoDtlCd><wlfareInfoReldNm>군산시 저장강박 의심가구 지원 조례</wlfareInfoReldNm></baslawList></wantedDtl>