<?xml version="1.0" encoding="UTF-8" standalone="yes"?><wantedDtl><resultCode>0</resultCode><resultMessage>SUCCESS</resultMessage><servId>WLF00006524</servId><servNm>전북 청년 1인 소상공인농어업인 출산급여 지원사업</servNm><enfcBgngYmd>20260121</enfcBgngYmd><enfcEndYmd>99991231</enfcEndYmd><bizChrDeptNm>전북특별자치도 기획조정실 인구청년정책과</bizChrDeptNm><ctpvNm>전북특별자치도</ctpvNm><servDgst>임신‧출산으로 인한 경영 공백 및 인력채용 등에 어려움을 겪는 소상공인·농어업인의 출산과 양육 지원을 통해 저출생 극복을 위한 사회적 기반 조성</servDgst><lifeNmArray>영유아</lifeNmArray><intrsThemaNmArray>서민금융</intrsThemaNmArray><sprtCycNm>월</sprtCycNm><srvPvsnNm>현금지급</srvPvsnNm><aplyMtdNm>방문</aplyMtdNm><sprtTrgtCn>청년 1인 소상공인․농어업인 본인 또는 배우자 출산 시 출산급여 지원 
- 본인 출산 시 90만원, 배우자 출산 시 출산휴가지원금 80만원</sprtTrgtCn><slctCritCn>0 출산급여 지원대상 :출산한 청년 1인 소상공인․농어업인
 - (자격요건) 공고일 기준 6개월 이상 전북도에 거주하고, 도내에서 ①사업장을 운영중인 1인 소상공인 또는 ②농어업을 영위하고 있는 농어업인으로서 '26. 1. 1. 이후 출산하고 도내에 자녀 출생신고를 완료한 자, 출산일로부터 1년 이내 신청 

0 출산휴가지원금 지원대상 : 출산한 배우자를 둔 청년 1인 소상공인․농어업인
 - (자격요건) 공고일 기준 6개월 이상 전북도에 거주하고, 도내에서 ①사업장을 운영중인 1인 소상공인 또는 ②농어업을 영위하고 있는 농어업인으로서 '26. 1. 1. 이후 출산하고 도내에 자녀 출생신고를 완료한 자, 배우자 출산일로부터 1년 이내 신청 
</slctCritCn><alwServCn>본인 출산 시 90만원, 배우자 출산 시 출산휴가지원금 80만원</alwServCn><aplyMtdCn>청년 1인 소상공인농어업인 출산급여 지원사업 담당부서에 문의(공고 등 확인)</aplyMtdCn><inqNum>58</inqNum><lastModYmd>20260704</lastModYmd><inqplCtadrList><wlfareInfoDtlCd>010</wlfareInfoDtlCd><wlfareInfoReldCn>063-280-3942</wlfareInfoReldCn><wlfareInfoReldNm>전북특별자치도 인구청년정책과</wlfareInfoReldNm></inqplCtadrList><baslawList><wlfareInfoDtlCd>030</wlfareInfoDtlCd><wlfareInfoReldNm>전북특별자치도 저출산·고령사회 대책 지원 조례</wlfareInfoReldNm></baslawList></wantedDtl>