<?xml version="1.0" encoding="UTF-8" standalone="yes"?><wantedDtl><resultCode>0</resultCode><resultMessage>SUCCESS</resultMessage><servId>WLF00005981</servId><servNm>가평군 청년 1인가구 월세 지원사업</servNm><enfcBgngYmd>20231107</enfcBgngYmd><enfcEndYmd>99991231</enfcEndYmd><bizChrDeptNm>경기도 가평군 기획예산담당관</bizChrDeptNm><ctpvNm>경기도</ctpvNm><sggNm>가평군</sggNm><servDgst>청년들의 안정적인 정주기반 조성을 위해 지역 정착을 유도하고 순유출을 방지하고자 관내 청년들에게 월세 자금을 지원</servDgst><lifeNmArray>청년</lifeNmArray><intrsThemaNmArray>서민금융</intrsThemaNmArray><sprtCycNm>분기</sprtCycNm><srvPvsnNm>현금지급</srvPvsnNm><aplyMtdNm>방문, 우편, 인터넷</aplyMtdNm><sprtTrgtCn>지원대상: 주민등록상 가평군 거주 19~39세의 독립거주 청년 1인 가구
(소득기준) 기준 중위소득 150% 이하 // 원가구 소득 반영(취·창업자 제외)
(주택기준) 임차보증금 1억 원 이하 및 월세 60만원 이하
(근로기준) 취·창업으로 소득이 발생하는 자 또는 학생·취업준비생 등
</sprtTrgtCn><slctCritCn>지원대상: 주민등록상 가평군 거주 19~39세의 독립거주 청년 1인 가구
(소득기준) 기준 중위소득 150% 이하 // 원가구 소득 반영(취·창업자 제외)
(주택기준) 임차보증금 1억 원 이하 및 월세 60만원 이하
(근로기준) 취·창업으로 소득이 발생하는 자 또는 학생·취업준비생 등
</slctCritCn><alwServCn>분기별 기 납부 월세 3개월분 합산금액 최대 60만원 지원</alwServCn><aplyMtdCn>1. 가평군청 기획예산담당관 방문 및 우편 접수
2. 경기도 일자리재단 통합접수시스템 접수</aplyMtdCn><inqNum>11825</inqNum><lastModYmd>20260703</lastModYmd><inqplCtadrList><wlfareInfoDtlCd>010</wlfareInfoDtlCd><wlfareInfoReldCn>031-580-2388</wlfareInfoReldCn><wlfareInfoReldNm>가평군청 기획예산담당관 인구정책팀</wlfareInfoReldNm></inqplCtadrList><baslawList><wlfareInfoDtlCd>030</wlfareInfoDtlCd><wlfareInfoReldNm>가평군 인구정책 지원 조례</wlfareInfoReldNm></baslawList><basfrmList><wlfareInfoDtlCd>040</wlfareInfoDtlCd><wlfareInfoReldCn>https://www.bokjiro.go.kr/ssis-tbu/CmmFileUtil/siteQnaInfoDownload.do?atcflId=20260617UUWBM1104210197369215&amp;atcflSn=1</wlfareInfoReldCn><wlfareInfoReldNm>가평군 인구정책 지원 조례 (청년월세 근거).pdf</wlfareInfoReldNm></basfrmList></wantedDtl>