<?xml version="1.0" encoding="UTF-8" standalone="yes"?><wantedDtl><resultCode>0</resultCode><resultMessage>SUCCESS</resultMessage><servId>WLF00004330</servId><servNm>저소득층 자녀 장학금 지원 사업</servNm><enfcBgngYmd>20071105</enfcBgngYmd><enfcEndYmd>99991231</enfcEndYmd><bizChrDeptNm>경상남도 함양군 경제복지국 노인복지과</bizChrDeptNm><ctpvNm>경상남도</ctpvNm><sggNm>함양군</sggNm><servDgst>함양군내에 거주하는 저소득 주민 자녀에게 지급하는 장학금 지원 사업입니다.</servDgst><lifeNmArray>청소년</lifeNmArray><trgterIndvdlNmArray>저소득</trgterIndvdlNmArray><intrsThemaNmArray>교육, 서민금융</intrsThemaNmArray><sprtCycNm>반기</sprtCycNm><srvPvsnNm>현금지급</srvPvsnNm><sprtTrgtCn>1. 군내에 주소를 두고 있는 대상
2. 품행이 바르고 다른 학생의 모범이 되는 중·고등학교 재학생
3. 국민기초생활보장법에 따른 수급자의 자녀</sprtTrgtCn><slctCritCn>저소득(기초수급자) 대상자 중에서 지원함</slctCritCn><alwServCn>ㅇ 장학금은 연2회, 상.하반기로 구분하여 지급
  - 일반장학금
      (상반기)중학생 200,000원, 고등학생 300,000원
      (하반기)중학생 200,000원, 고등학생 300,000원
  - 특별장학금
      (상반기)중학생 300,000원, 고등학생 400,000원
      (하반기)중학생 300,000원, 고등학생 400,000원</alwServCn><inqNum>2309</inqNum><lastModYmd>20260703</lastModYmd><inqplCtadrList><wlfareInfoDtlCd>010</wlfareInfoDtlCd><wlfareInfoReldCn>055-960-4930</wlfareInfoReldCn><wlfareInfoReldNm>함양군청 노인복지과 기초생활담당</wlfareInfoReldNm></inqplCtadrList><baslawList><wlfareInfoDtlCd>030</wlfareInfoDtlCd><wlfareInfoReldNm>함양군사회복지통합기금설치운용조례</wlfareInfoReldNm></baslawList><basfrmList><wlfareInfoDtlCd>040</wlfareInfoDtlCd><wlfareInfoReldCn>https://www.bokjiro.go.kr/ssis-tbu/CmmFileUtil/siteQnaInfoDownload.do?atcflId=4498GOWF15GOWF154498&amp;atcflSn=1</wlfareInfoReldCn><wlfareInfoReldNm>함양군 사회복지통합기금 설치 및 운용 조례.hwp</wlfareInfoReldNm></basfrmList></wantedDtl>