<?xml version="1.0" encoding="UTF-8" standalone="yes"?><wantedDtl><resultCode>0</resultCode><resultMessage>SUCCESS</resultMessage><servId>WLF00004165</servId><servNm>공공근로사업</servNm><enfcBgngYmd>20140101</enfcBgngYmd><enfcEndYmd>99991231</enfcEndYmd><bizChrDeptNm>경상남도 밀양시 나노경제국 지역경제과</bizChrDeptNm><ctpvNm>경상남도</ctpvNm><sggNm>밀양시</sggNm><servDgst>지역 실정에 맞는 사업을 발굴, 추진하여 취업취약계층 실업자에게 구직기간 동안 한시적으로 공공부문의 일자리를 제공하여 생계보조를 통한 사회 안전망 역할 및 근로 기회 부여</servDgst><lifeNmArray>청년, 중장년, 노년</lifeNmArray><trgterIndvdlNmArray>다문화·탈북민, 보훈대상자</trgterIndvdlNmArray><intrsThemaNmArray>일자리, 입양·위탁, 서민금융</intrsThemaNmArray><sprtCycNm>월</sprtCycNm><srvPvsnNm>현금지급</srvPvsnNm><aplyMtdNm>방문</aplyMtdNm><sprtTrgtCn>1)신청대상
 - 신청일 현재 만18세 이상 만 70세 미만인 자로서 실업자 또는 정기소득이 없는 일용근로자로서 구직등록을 한 자 
2) 대상자 선정
  - 공공근로사업추진위원회 심의를 거친 선발기준에 의거 선발</sprtTrgtCn><slctCritCn>가구소득이 기준중위소득 60% 이하
재산 3억원 이하</slctCritCn><alwServCn> 근무시간
    - 청년(18세~39세): 1일 6시간, 주 30시간 이내(주 5일)
    - 65세 미만: 1일 6시간, 주 24시간 이내(주 4일)
    - 65세 이상: 1일 5시간, 주 15시간 이내(주 3일)</alwServCn><aplyMtdCn>1) 신청방법 : 읍/면/동행정복지센터로 신청
2) 신청시기 
  - 상반기: 2025. 12. 29. ~ 2026. 1. 7.
  - 하반기: 2026. 6. 17. ~ 6. 24.</aplyMtdCn><inqNum>11480</inqNum><lastModYmd>20260703</lastModYmd><inqplCtadrList><wlfareInfoDtlCd>010</wlfareInfoDtlCd><wlfareInfoReldCn>055-359-5058</wlfareInfoReldCn><wlfareInfoReldNm>밀양시 나노경제국 지역경제과</wlfareInfoReldNm></inqplCtadrList><baslawList><wlfareInfoDtlCd>030</wlfareInfoDtlCd><wlfareInfoReldNm>고용정책기본법 제6조(국가와 지방자치단체의 시책)</wlfareInfoReldNm></baslawList><basfrmList><wlfareInfoDtlCd>040</wlfareInfoDtlCd><wlfareInfoReldCn>https://www.bokjiro.go.kr/ssis-tbu/CmmFileUtil/siteQnaInfoDownload.do?atcflId=20250612UUWBM0914490141699902&amp;atcflSn=1</wlfareInfoReldCn><wlfareInfoReldNm>2025년 공공근로사업 지침(안).hwp</wlfareInfoReldNm></basfrmList></wantedDtl>