<?xml version="1.0" encoding="UTF-8" standalone="yes"?><wantedDtl><resultCode>0</resultCode><resultMessage>SUCCESS</resultMessage><servId>WLF00004483</servId><servNm>난임부부 격려금 지원</servNm><enfcBgngYmd>20130101</enfcBgngYmd><enfcEndYmd>99991231</enfcEndYmd><bizChrDeptNm>경상남도 진주시 보건소 건강증진과</bizChrDeptNm><ctpvNm>경상남도</ctpvNm><sggNm>진주시</sggNm><servDgst>난임의 정상적인 시술을 받았으나 임신이 되지 않아 겪는 정신.육체.경제적 부담을 경감하기 위하여 지급.</servDgst><lifeNmArray>청년, 중장년</lifeNmArray><intrsThemaNmArray>서민금융</intrsThemaNmArray><sprtCycNm>수시</sprtCycNm><srvPvsnNm>현금지급</srvPvsnNm><aplyMtdNm>방문</aplyMtdNm><sprtTrgtCn> - 난임부부 격려금 : 시술을 한 날부터 지원신청일 현재까지 진주시 관내에 주민등록이 되어 있는 난임부부로서 정상 난임시술을 했으나 비 임신시 매회당 20만원 지원</sprtTrgtCn><slctCritCn>시술을 시작한 날부터 지원신청일 현재까지 진주시 관내에 주민등록이 되어 있는 난임부부로서 정상 난임시술을 했으나 비 임신시 매회당 20만원 지원</slctCritCn><alwServCn>- 난임부부 격려금 : 격려금 20만원 지원</alwServCn><aplyMtdCn>- 진주시보건소 건강증진과 방문신청</aplyMtdCn><inqNum>2285</inqNum><lastModYmd>20250815</lastModYmd><inqplCtadrList><wlfareInfoDtlCd>010</wlfareInfoDtlCd><wlfareInfoReldCn>055-749-5775</wlfareInfoReldCn><wlfareInfoReldNm>진주시보건소 건강증진과 </wlfareInfoReldNm></inqplCtadrList><baslawList><wlfareInfoDtlCd>030</wlfareInfoDtlCd><wlfareInfoReldNm>진주시 출산장려 지원에 관한 조례</wlfareInfoReldNm></baslawList><basfrmList><wlfareInfoDtlCd>040</wlfareInfoDtlCd><wlfareInfoReldCn>https://www.bokjiro.go.kr/ssis-tbu/CmmFileUtil/siteQnaInfoDownload.do?atcflId=0351GOWF15GOWF150351&amp;atcflSn=1</wlfareInfoReldCn><wlfareInfoReldNm>진주시 출산장려 지원에 관한 조례(격려금).hwp</wlfareInfoReldNm></basfrmList></wantedDtl>