<?xml version="1.0" encoding="UTF-8" standalone="yes"?><wantedDtl><resultCode>0</resultCode><resultMessage>SUCCESS</resultMessage><servId>WLF00005919</servId><servNm>안산시 다자녀 가정 렌터카 지원 사업(넷째아 이상 다자녀 가정 차량(대여) 지원 사업)</servNm><enfcBgngYmd>20250601</enfcBgngYmd><enfcEndYmd>99991231</enfcEndYmd><bizChrDeptNm>경기도 안산시 복지국 여성보육과</bizChrDeptNm><ctpvNm>경기도</ctpvNm><sggNm>안산시</sggNm><servDgst>다자녀 가정의 이동 편의를 지원하여 가족 단위 여가 활동 활성화에 기여하고, 가족친화 사회환경 조성 및 경제적 부담 경감하여 출산·양육하기 좋은 환경을 조성하기 위한 사업</servDgst><trgterIndvdlNmArray>다자녀</trgterIndvdlNmArray><intrsThemaNmArray>서민금융</intrsThemaNmArray><sprtCycNm>1회성</sprtCycNm><srvPvsnNm>현물대여</srvPvsnNm><aplyMtdNm>인터넷</aplyMtdNm><sprtTrgtCn>안산시에 거주하고 자녀 4명 중 1명 이상이 만 18세 이하인 가정을 지원합니다.
(단, 부 또는 모와 자녀 2명 이상이 등본상 안산시 같은 주소로 등록, 6세 미만 자녀 탑승 시 개인 카시트 지참 및 장착 가능해야 함)</sprtTrgtCn><slctCritCn>아래 4가지 조건을 모두 충족해야 합니다
1. 안산시에 거주하며, 부 또는 모와 자녀 2명 이상이 같은 세대로 주민등록 되어 있는 가정
2. 가족관계증명서상 자녀가 4명인 가정
3. 4자녀 중 1명 이상이 만 18세 이하인 가정
4. 6세미만 영유아 탑승 시, 개인 카시트 소지하고 장착할 수 있는 가정
※ 운전자는 만 26세 이상, 운전면허 취득 2년 이상자에 한하며, 운전자는 1명 추가 가능</slctCritCn><alwServCn>■ 1가정당 연 1회, 최대 3일 이내의 렌터카 대여료를 지원합니다. (※ 분할 이용 불가)
   · 차량종류 : 6인승(쏘렌토, 산타페), 9인승(카니발), 11인승(스타리아)
※ 대여료 외 유류비, 자기부담보험료, 과태료 등 추가비용은 본인 부담입니다.</alwServCn><aplyMtdCn>■ 신청방법 : 이용일 기준 한 달 전부터 최소 2주일 전까지 ‘안산시 통합예약시스템’에서 온라인 신청
■ 제출서류 : 신분증, 주민등록등본1부 (※ 자녀 주소가 다를 경우 가족관계증명서 1부 추가 제출)</aplyMtdCn><inqNum>1658</inqNum><lastModYmd>20260703</lastModYmd><inqplCtadrList><wlfareInfoDtlCd>010</wlfareInfoDtlCd><wlfareInfoReldCn>031-481-2606</wlfareInfoReldCn><wlfareInfoReldNm>안산시청 여성보육과</wlfareInfoReldNm></inqplCtadrList><baslawList><wlfareInfoDtlCd>030</wlfareInfoDtlCd><wlfareInfoReldNm>안산시 출산장려 지원 등에 관한 조례</wlfareInfoReldNm></baslawList><basfrmList><wlfareInfoDtlCd>040</wlfareInfoDtlCd><wlfareInfoReldCn>https://www.bokjiro.go.kr/ssis-tbu/CmmFileUtil/siteQnaInfoDownload.do?atcflId=20250602UUWBM1545470140391978&amp;atcflSn=1</wlfareInfoReldCn><wlfareInfoReldNm>안산시 출산장려 지원 등에 관한 조례(경기도 안산시조례)(제2963호)(20241231).pdf</wlfareInfoReldNm></basfrmList></wantedDtl>