<?xml version="1.0" encoding="UTF-8" standalone="yes"?><wantedDtl><resultCode>0</resultCode><resultMessage>SUCCESS</resultMessage><servId>WLF00006125</servId><servNm>관악구 청년 어학·자격시험 응시료 지원</servNm><enfcBgngYmd>20240601</enfcBgngYmd><enfcEndYmd>99991231</enfcEndYmd><bizChrDeptNm>서울특별시 관악구 청년문화국 청년정책과</bizChrDeptNm><ctpvNm>서울특별시</ctpvNm><sggNm>관악구</sggNm><servDgst>관악구 거주 만19~39세 미취업청년에게 어학·자격시험 응시료를 지원을 통해 취업준비비용 부담을 완화하고 취업역량을 강화하여 취업률 향상을 도모하고자 함</servDgst><lifeNmArray>청년</lifeNmArray><intrsThemaNmArray>일자리, 서민금융</intrsThemaNmArray><sprtCycNm>년</sprtCycNm><srvPvsnNm>현금지급</srvPvsnNm><aplyMtdNm>인터넷</aplyMtdNm><sprtTrgtCn> ○ 지원대상 : 관악구 거주 19~39세 미취업 청년(1986년∼2007년생)
   - 신청일 기준 주민등록상 관악구 거주
   - 응시일부터 신청일까지 미취업 및 사업자 미등록 청년
   - 2026년 1월 1일 이후 실시한 국가기술(전문)자격시험, 국가공인자격시험,
     어학시험(토익 등), 한국사능력검정시험 등 각종 자격시험에 응시한 자</sprtTrgtCn><slctCritCn>주민등록상 관악구 거주 중인 19~39세 미취업 청년 중 당해연도 어학, 국가기술(전문)자격시험, 국가공인자격시험, 한국사능력검증시험 등에 응시한 자
(경찰청 주관 자동차운전면허 제외)

1. 연령(만19~39세)
2. 주소(관악구 거주)
3. 응시일부터 신청시까지 미취업 및 사업자 미등록여부  ※ 단, 주 26시간 이하 또는 3개월 이하 단기 근로자는 지원 가능
4. 2026년 시험 실제 응시여부 및 응시료 지출 증빙
5. 제외대상: 정부 및 타지자체 등으로부터 유사사업 중복지급 받지 않은 자(서울시 청년수당, 국민취업지원제도, 타 지자체 응시료 지원사업)
</slctCritCn><alwServCn>1인당 연 1회 최대 10만원 응시료 실비 지원(응시시험 통합 1회 신청)</alwServCn><aplyMtdCn>관악구청 홈페이지 온라인 신청
- 참여/예약(참여신청→행정접수) 접수하기 클릭
- 관악구청 홈페이지 내 신청서 및 개인정보 수집이용 동의서 다운받아 회원가입 후 신청
- 전체 증빙서류 첨부</aplyMtdCn><inqNum>4740</inqNum><lastModYmd>20260704</lastModYmd><inqplCtadrList><wlfareInfoDtlCd>010</wlfareInfoDtlCd><wlfareInfoReldCn>02-879-5932</wlfareInfoReldCn><wlfareInfoReldNm>관악구 청년정책과</wlfareInfoReldNm></inqplCtadrList><baslawList><wlfareInfoDtlCd>030</wlfareInfoDtlCd><wlfareInfoReldNm>「서울특별시 관악구 청년일자리 창출 촉진에 관한 조례」제6조(사업 추진·지원)</wlfareInfoReldNm></baslawList><basfrmList><wlfareInfoDtlCd>040</wlfareInfoDtlCd><wlfareInfoReldCn>https://www.bokjiro.go.kr/ssis-tbu/CmmFileUtil/siteQnaInfoDownload.do?atcflId=20250708UUWBM1500040145342386&amp;atcflSn=1</wlfareInfoReldCn><wlfareInfoReldNm>[붙임2] 응시료 지원신청서 및 개인정보이용 동의서.hwp</wlfareInfoReldNm></basfrmList></wantedDtl>