<?xml version="1.0" encoding="UTF-8" standalone="yes"?><wantedDtl><resultCode>0</resultCode><resultMessage>SUCCESS</resultMessage><servId>WLF00000042</servId><servNm>다자녀세대 체험놀이 지원</servNm><enfcBgngYmd>20190101</enfcBgngYmd><enfcEndYmd>99991231</enfcEndYmd><bizChrDeptNm>경상남도 고성군 부군수 인구청년추진단</bizChrDeptNm><ctpvNm>경상남도</ctpvNm><sggNm>고성군</sggNm><servDgst>다자녀세대 지원의 일환으로 다자녀 세대 대상 양육하기 좋은 사회 친화적 분위기 조성 및 관내 체험업체와의 상생 도모</servDgst><lifeNmArray>아동, 청소년</lifeNmArray><intrsThemaNmArray>입양·위탁</intrsThemaNmArray><sprtCycNm>1회성</sprtCycNm><srvPvsnNm>실물바우처</srvPvsnNm><aplyMtdNm>방문</aplyMtdNm><sprtTrgtCn>○ 부모와 자녀 모두 군에 주민등록을 두고 있는 1가구 2자녀 이상 세대 중 18세 이하 자녀를 둔 세대
  - 1인당 2만원 상당의 체험놀이이용권 지급</sprtTrgtCn><slctCritCn>○ 부모와 자녀 모두 군에 주민등록을 두고 있는 1가구 2자녀 이상 세대 중 18세 이하 자녀를 둔 세대
</slctCritCn><alwServCn>○부모와 자녀 모두 군에 주민등록을 두고 있는 1가구 2자녀 이상 세대 중 18세 이하 자녀를 둔 세대
  - 1인당 2만원 상당의 체험놀이이용권 지급</alwServCn><aplyMtdCn>신청(읍면) → 지원조건확인(읍면) → 이용권 배부</aplyMtdCn><inqNum>1336</inqNum><lastModYmd>20260630</lastModYmd><inqplCtadrList><wlfareInfoDtlCd>010</wlfareInfoDtlCd><wlfareInfoReldCn>055-670-2705</wlfareInfoReldCn><wlfareInfoReldNm>고성군 인구청년추진단</wlfareInfoReldNm></inqplCtadrList><baslawList><wlfareInfoDtlCd>030</wlfareInfoDtlCd><wlfareInfoReldNm>고성군 인구증가 시책에 관한 조례 제3조</wlfareInfoReldNm></baslawList><basfrmList><wlfareInfoDtlCd>040</wlfareInfoDtlCd><wlfareInfoReldCn>https://www.bokjiro.go.kr/ssis-tbu/CmmFileUtil/siteQnaInfoDownload.do?atcflId=6746GOWF15GOWF156746&amp;atcflSn=1</wlfareInfoReldCn><wlfareInfoReldNm>다자녀세대 지원사업(체험놀이) 확대 계획.pdf</wlfareInfoReldNm></basfrmList></wantedDtl>