<?xml version="1.0" encoding="UTF-8" standalone="yes"?><wantedDtl><resultCode>0</resultCode><resultMessage>SUCCESS</resultMessage><servId>WLF00006351</servId><servNm>서울특별시 강서구 전세피해임차인 지원사업</servNm><enfcBgngYmd>20230906</enfcBgngYmd><enfcEndYmd>99991231</enfcEndYmd><bizChrDeptNm>서울특별시 강서구 도시관리국 부동산정보과</bizChrDeptNm><ctpvNm>서울특별시</ctpvNm><sggNm>강서구</sggNm><servDgst>전세피해 주택임차인의 피해 회복 지원으로 주거안정 및 주거복지 향상 기여</servDgst><intrsThemaNmArray>서민금융</intrsThemaNmArray><sprtCycNm>1회성</sprtCycNm><srvPvsnNm>현금지급</srvPvsnNm><aplyMtdNm>방문, 인터넷</aplyMtdNm><sprtTrgtCn>아래 요건 모두 충족하는 경우 지원 가능
 (공통)
 1. 서울시 강서구의 주택을 임차한 사람(강서구 거주하거나 거주할 예정)
 2. 무주택자인 전세피해자 또는 전세사기피해자
    * 전세피해자: 주택도시보증공사(HUG)에서 발급한 확인서를 받은 사람
    * 전세사기피해자:「전세사기피해자 지원 및 주거안정에 관한 특별법」제3조의 요건을 갖춰 국토교통부장관이 결정한 임차인
 
 (사업별 요건)
 ① 전세보증금 반환보증 보증료 지원: 새로운 전‧월세 주택으로 입주하여 보증료를 납부한 자 
 ② 긴급지원주택 입주자 이사비 지원: ‘긴급주거지원’ 및 ‘인근 공공임대 우선공급’에 따라
    공공임대주택으로 입주한 자
 ③ 월세지원: 민간 월세 주택으로 입주한 청년(19세~39세) 중 월세를 1회 이상 납부한 자
 ④ 소송수행경비 지원: 보증금 회수를 위한 법적 절차 이행 시 경비가 필요한 자
   - 보증금지급명령, 보증금반환청구 소송 등 수행 경비(송달료, 인지대 등) 지원</sprtTrgtCn><slctCritCn>(선정기준 상세내용) 
 아래 요건 모두 충족하는 경우 지원 가능
 (공통)
 1. 서울시 강서구의 주택을 임차한 사람(강서구 거주하거나 거주할 예정)
 2. 무주택자인 전세피해자 또는 전세사기피해자
    * 전세피해자: 주택도시보증공사(HUG)에서 발급한 확인서를 받은 사람
    * 전세사기피해자:「전세사기피해자 지원 및 주거안정에 관한 특별법」제3조의 요건을                       갖춰 국토교통부장관이 결정한 임차인
    
 「전세사기피해자 지원 및 주거안정에 관한 특별법」제3조의 요건
  - 주택의 인도와 주민등록(전입신고)을 마치고 확정일자를 갖춘 경우
  - 임대차보증금이 5억원 이하인 경우
  - 2인 이상의 임차인에게 임대차보증금반환채권의 변제를 받지 못하는 피해가 발생하였
    거나 발생할 것이 예상되는 경우
  - 임대인이 임차보증금반환채무를 이행하지 아니할 의도가 있었다고 의심할만한 상당한     이유가 있는 경우

 (사업별 요건)
 ① 전세보증금 반환보증 보증료 지원: 새로운 전‧월세 주택으로 입주하여 보증료를 납부한 자 
 ② 긴급지원주택 입주자 이사비 지원: ‘긴급주거지원’ 및 ‘인근 공공임대 우선공급’에 따라
    공공임대주택으로 입주한 자
 ③ 월세지원: 민간 월세 주택으로 입주한 청년(19세~39세) 중 월세를 1회 이상 납부한 자
 ④ 소송수행경비 지원: 보증금 회수를 위한 법적 절차 이행 시 경비가 필요한 자
   - 보증금지급명령, 보증금반환청구 소송 등 수행 경비(송달료, 인지대 등) 지원
   ※ 전세피해지원금의 지원은 조례 부칙 개정에 따라 공포일(’23.07.26.)로부터 4년간 유효함.</slctCritCn><alwServCn>전세피해자 지원금(택1, 중복불가, 소급적용, 소득기준 적용 없음)
 ① 전세보증금 반환보증 보증료 지원: 100만원 이내(실비)/1회
 ② 긴급지원주택 입주자 이사비 지원: 100만원 이내(실비)/1회
 ③ 청년월세 지원: 월 20만원 이내(실비)/최대 12개월
 ④ 소송수행 경비 지원: 100만원(정액)/1회</alwServCn><aplyMtdCn>(오프라인)서울 강서구청 1층 부동산정보과 방문 신청
(온라인) 정부24에서 강서구 전세피해지원금 검색 후 신청</aplyMtdCn><inqNum>106</inqNum><lastModYmd>20260630</lastModYmd><inqplCtadrList><wlfareInfoDtlCd>010</wlfareInfoDtlCd><wlfareInfoReldCn>02-2600-6907</wlfareInfoReldCn><wlfareInfoReldNm>서울특별시 강서구청 부동산정보과</wlfareInfoReldNm></inqplCtadrList><inqplCtadrList><wlfareInfoDtlCd>010</wlfareInfoDtlCd><wlfareInfoReldCn>02-2600-6891</wlfareInfoReldCn><wlfareInfoReldNm>서울특별시 강서구청 부동산정보과</wlfareInfoReldNm></inqplCtadrList><baslawList><wlfareInfoDtlCd>030</wlfareInfoDtlCd><wlfareInfoReldNm>서울특별시 강서구 전세피해 및 전세사기피해자 지원 조례 제7조</wlfareInfoReldNm></baslawList><basfrmList><wlfareInfoDtlCd>040</wlfareInfoDtlCd><wlfareInfoReldCn>https://www.bokjiro.go.kr/ssis-tbu/CmmFileUtil/siteQnaInfoDownload.do?atcflId=20260610UUWBM1116360196245114&amp;atcflSn=1</wlfareInfoReldCn><wlfareInfoReldNm>서울특별시 강서구 전세피해 및 전세사기피해자 지원 조례.hwp</wlfareInfoReldNm></basfrmList><basfrmList><wlfareInfoDtlCd>040</wlfareInfoDtlCd><wlfareInfoReldCn>https://www.bokjiro.go.kr/ssis-tbu/CmmFileUtil/siteQnaInfoDownload.do?atcflId=20260610UUWBM1135420196252686&amp;atcflSn=1</wlfareInfoReldCn><wlfareInfoReldNm>전세사기 피해지원 신청서.hwp</wlfareInfoReldNm></basfrmList><basfrmList><wlfareInfoDtlCd>040</wlfareInfoDtlCd><wlfareInfoReldCn>https://www.bokjiro.go.kr/ssis-tbu/CmmFileUtil/siteQnaInfoDownload.do?atcflId=20260610UUWBM1136470196253806&amp;atcflSn=1</wlfareInfoReldCn><wlfareInfoReldNm>개인정보 수집·이용 등 동의서.hwp</wlfareInfoReldNm></basfrmList><basfrmList><wlfareInfoDtlCd>040</wlfareInfoDtlCd><wlfareInfoReldCn>https://www.bokjiro.go.kr/ssis-tbu/CmmFileUtil/siteQnaInfoDownload.do?atcflId=20260610UUWBM1138070196253961&amp;atcflSn=1</wlfareInfoReldCn><wlfareInfoReldNm>전세사기 피해지원 신청 위임장.hwp</wlfareInfoReldNm></basfrmList></wantedDtl>