<?xml version="1.0" encoding="UTF-8" standalone="yes"?><wantedDtl><resultCode>0</resultCode><resultMessage>SUCCESS</resultMessage><servId>WLF00000626</servId><servNm>효행장려금 지급</servNm><enfcBgngYmd>20160801</enfcBgngYmd><enfcEndYmd>99991231</enfcEndYmd><bizChrDeptNm>충청남도 태안군 행정안전국 가족정책과</bizChrDeptNm><ctpvNm>충청남도</ctpvNm><sggNm>태안군</sggNm><servDgst>효 장려 및  경로사상 증진</servDgst><lifeNmArray>노년</lifeNmArray><intrsThemaNmArray>서민금융</intrsThemaNmArray><sprtCycNm>년</sprtCycNm><srvPvsnNm>현금지급</srvPvsnNm><aplyMtdNm>방문</aplyMtdNm><sprtTrgtCn>70세 이상의 직계존손과 직계비속을 합하여 3대 이상이 태안군에 1년 이상 주민등록을 같이 하고 함께 거주하는 가정</sprtTrgtCn><slctCritCn>70세 이상 직계존비속을 포함하여 3대 이상이 태안군에 1년 이상 주민등록을 같이 하고 함께 거주하는 가정</slctCritCn><alwServCn>매년 1회 30만원 지급</alwServCn><aplyMtdCn>주소지 읍면 행정복지센터 신청 -&gt; 군에서 효행장려금 지급</aplyMtdCn><inqNum>1276</inqNum><lastModYmd>20250807</lastModYmd><inqplCtadrList><wlfareInfoDtlCd>010</wlfareInfoDtlCd><wlfareInfoReldCn>041-670-2267</wlfareInfoReldCn><wlfareInfoReldNm>태안군청 가족정책과 노인복지팀</wlfareInfoReldNm></inqplCtadrList><baslawList><wlfareInfoDtlCd>030</wlfareInfoDtlCd><wlfareInfoReldNm>태안군 효행장려 및 지원에 관한 조례</wlfareInfoReldNm></baslawList><basfrmList><wlfareInfoDtlCd>040</wlfareInfoDtlCd><wlfareInfoReldCn>https://www.bokjiro.go.kr/ssis-tbu/CmmFileUtil/siteQnaInfoDownload.do?atcflId=20240603UUWBM1025260087806161&amp;atcflSn=1</wlfareInfoReldCn><wlfareInfoReldNm>(본문) 2023년 효행장려금 지원계획.hwpx</wlfareInfoReldNm></basfrmList></wantedDtl>