<?xml version="1.0" encoding="UTF-8" standalone="yes"?><wantedDtl><resultCode>0</resultCode><resultMessage>SUCCESS</resultMessage><servId>WLF00001561</servId><servNm>효행장려금</servNm><enfcBgngYmd>20170101</enfcBgngYmd><enfcEndYmd>99991231</enfcEndYmd><bizChrDeptNm>경기도 광명시 사회복지국 어르신복지과</bizChrDeptNm><ctpvNm>경기도</ctpvNm><sggNm>광명시</sggNm><servDgst>아름다운 전통문화유산인 효를 적극 장려하고 지원함으로써 효행을 통하여 고령화에 따른 사회문제를 해결하고 노인의 삶의 질 향상과 효행문화 발전에 이바지하고자 함</servDgst><lifeNmArray>노년</lifeNmArray><intrsThemaNmArray>서민금융</intrsThemaNmArray><sprtCycNm>1회성</sprtCycNm><srvPvsnNm>현금지급</srvPvsnNm><aplyMtdNm>방문</aplyMtdNm><sprtTrgtCn>만 75세이상 직계존비속을 포함, 3대 이상이 주민등록상 한 세대를 구성하여  
광명시에 2년이상 주소를 두고 실제로 생활하는 가정의 실질적 부양자</sprtTrgtCn><slctCritCn>만75세이상 직계존비속포함 3대이상이 한 세대를 구성하고 이를 실제 부양하며 광명시 2년이상 거주한 자</slctCritCn><alwServCn>연 1회 가구당 300천원 지급</alwServCn><aplyMtdCn>9월에 거주지 동 주민센터에 신청</aplyMtdCn><inqNum>1515</inqNum><lastModYmd>20260703</lastModYmd><inqplCtadrList><wlfareInfoDtlCd>010</wlfareInfoDtlCd><wlfareInfoReldCn>02-2680-2549</wlfareInfoReldCn><wlfareInfoReldNm>광명시 어르신복지과</wlfareInfoReldNm></inqplCtadrList><baslawList><wlfareInfoDtlCd>030</wlfareInfoDtlCd><wlfareInfoReldNm>광명시 효행 장려 및 지원에 관한 조례</wlfareInfoReldNm></baslawList><basfrmList><wlfareInfoDtlCd>040</wlfareInfoDtlCd><wlfareInfoReldCn>https://www.bokjiro.go.kr/ssis-tbu/CmmFileUtil/siteQnaInfoDownload.do?atcflId=3610GOWF15GOWF153610&amp;atcflSn=1</wlfareInfoReldCn><wlfareInfoReldNm>광명시 효행 장려 및 지원에 관한 조례.pdf</wlfareInfoReldNm></basfrmList></wantedDtl>