<?xml version="1.0" encoding="UTF-8" standalone="yes"?><wantedDtl><resultCode>0</resultCode><resultMessage>SUCCESS</resultMessage><servId>WLF00006358</servId><servNm>양평군 전세사기 임차인 이주비 지원</servNm><enfcBgngYmd>20250701</enfcBgngYmd><enfcEndYmd>99991231</enfcEndYmd><bizChrDeptNm>경기도 양평군 문화복지국 민원토지과</bizChrDeptNm><ctpvNm>경기도</ctpvNm><sggNm>양평군</sggNm><servDgst>『전세사기피해자 지원 및 주거안정에 관한 특별법 제4조제4호』에 따라 관내 주거환경에 적합한 맞춤형 경제적 지원을 통해 관내 민간 임대주택으로 긴박히 이주하는 관내 전세사기피해자의 주거안정에 기여</servDgst><intrsThemaNmArray>서민금융</intrsThemaNmArray><sprtCycNm>1회성</sprtCycNm><srvPvsnNm>현금지급</srvPvsnNm><aplyMtdNm>방문</aplyMtdNm><sprtTrgtCn>○ 지원대상 : 전세사기 피해자 중 아래 요건을 모두 충족하는 자(전세사기피해자등 결정된 자 / 전세피해확인서를 받은자) 
  - 전세사기피해주택이 양평군 소재 
  - 양평군 소재 민간주택에 이주하여 실제 거주 및 주민등록을 마친 자 
  - 이주하는 주택임대차계약서 상 임차인과 본 사업대상자가 동일인일 것 </sprtTrgtCn><slctCritCn>(특별법)전세사기피해자등 결정된 자 또는 (HUG) 전세피해확인서를 받은 자 </slctCritCn><alwServCn>가구당 최대 150만원 이사비 지원 </alwServCn><aplyMtdCn>민원토지과 직접 방문 신청 </aplyMtdCn><inqNum>96</inqNum><lastModYmd>20260630</lastModYmd><inqplCtadrList><wlfareInfoDtlCd>010</wlfareInfoDtlCd><wlfareInfoReldCn>031-770-2047</wlfareInfoReldCn><wlfareInfoReldNm>양평군 민원토지과</wlfareInfoReldNm></inqplCtadrList><baslawList><wlfareInfoDtlCd>030</wlfareInfoDtlCd><wlfareInfoReldNm>양평군 주택임차인 보호 및 지원 조례</wlfareInfoReldNm></baslawList><basfrmList><wlfareInfoDtlCd>040</wlfareInfoDtlCd><wlfareInfoReldCn>https://www.bokjiro.go.kr/ssis-tbu/CmmFileUtil/siteQnaInfoDownload.do?atcflId=20260611UUWBM1100140196471125&amp;atcflSn=1</wlfareInfoReldCn><wlfareInfoReldNm>양평군 주택임차인 보호 및 지원 조례(경기도 양평군조례)(제3170호)(20250701).pdf</wlfareInfoReldNm></basfrmList></wantedDtl>