<?xml version="1.0" encoding="UTF-8" standalone="yes"?><wantedDtl><resultCode>0</resultCode><resultMessage>SUCCESS</resultMessage><servId>WLF00006168</servId><servNm>구미시 관외 대학교 통학생 교통비 지원사업</servNm><enfcBgngYmd>20250301</enfcBgngYmd><enfcEndYmd>99991231</enfcEndYmd><bizChrDeptNm>경상북도 구미시 미래교육돌봄국 인구청년과</bizChrDeptNm><ctpvNm>경상북도</ctpvNm><sggNm>구미시</sggNm><servDgst>관외 대학으로 통학하는 청년들의 교통비 부담완화를 통해 학업 지속과 생활안정을 이룰 수 있도록 지원하기 위함.</servDgst><lifeNmArray>청소년, 청년</lifeNmArray><intrsThemaNmArray>일자리, 서민금융</intrsThemaNmArray><sprtCycNm>반기</sprtCycNm><srvPvsnNm>지역화폐</srvPvsnNm><aplyMtdNm>인터넷</aplyMtdNm><sprtTrgtCn>신청일 기준 주민등록상 구미시에 6개월 이상 거주하고, 관외대학교로 철도 및 버스를 이용해 통학하는 19세~39세 대학(원)생을 지원합니다.
1. 연령 : 만19세 ~ 만39세
2. 주소 : 주민등록상 6개월 이상 구미시 거주
3. 교통 : 철도 및 버스 이용 통학
4. 기타 : 관외 대학교 재학생
</sprtTrgtCn><slctCritCn>신청일 기준 주민등록상 구미시에 6개월 이상 거주하고, 관외대학교로 철도 및 버스를 이용해 통학하는 19세~39세 대학(원)생을 지원합니다.
1. 연령 : 만19세 ~ 만39세
2. 주소 : 주민등록상 6개월 이상 구미시 거주
3. 교통 : 철도 및 버스 이용 통학
4. 기타 : 관외 대학교 재학생
 ※ 구미시 소재 대학교 재학생 및 휴학,졸업,자퇴,사이버대학 등 재학이 아닌 경우 지원하지 않습니다.</slctCritCn><alwServCn>신청일 기준 주민등록상 구미시에 6개월 이상 거주하고, 관외 대학교로 철도 또는 버스로 통학하는 19세~39세 대학(원)생을 지원합니다.
- 연 2회(상하반기) 분할 신청
- 이용 교통비의 정액 10만원을 카드형 구미사랑상품권으로 충전 지원(연 최대 20만원)
</alwServCn><aplyMtdCn>청년e끌림 회원가입 후 신청 가능합니다.
해당 사업 조회 &gt; 접수 &gt; 신청자 정보 입력 및 신청서, 재학증명서, 통학 이용 증빙서류, 구미사랑카드 사본, 주민등록초본(또는 개인정보제공동의서) 첨부 후 신청하시면 됩니다.
지원 여부 확인 후 카드형 구미사랑상품권으로 충전 지원합니다.</aplyMtdCn><inqNum>3550</inqNum><lastModYmd>20260630</lastModYmd><inqplCtadrList><wlfareInfoDtlCd>010</wlfareInfoDtlCd><wlfareInfoReldCn>054-480-2527</wlfareInfoReldCn><wlfareInfoReldNm>경상북도 구미시 미래교육돌봄국 인구청년과</wlfareInfoReldNm></inqplCtadrList><baslawList><wlfareInfoDtlCd>030</wlfareInfoDtlCd><wlfareInfoReldNm>구미시 인구정책 지원 조례 제6조, 구미시 청년 미취업자 취업 지원에 관한 조례 제4조</wlfareInfoReldNm></baslawList><basfrmList><wlfareInfoDtlCd>040</wlfareInfoDtlCd><wlfareInfoReldCn>https://www.bokjiro.go.kr/ssis-tbu/CmmFileUtil/siteQnaInfoDownload.do?atcflId=20260610UUWBM1103280196240289&amp;atcflSn=1</wlfareInfoReldCn><wlfareInfoReldNm>2026년 관외 대학교 통학생 교통비 지원사업 추진계획.pdf</wlfareInfoReldNm></basfrmList></wantedDtl>