<?xml version="1.0" encoding="UTF-8" standalone="yes"?><wantedDtl><servId>WLF00000100</servId><servNm>자산형성지원사업(희망저축계좌Ⅰ, Ⅱ)</servNm><jurMnofNm>보건복지부 자활정책과</jurMnofNm><tgtrDtlCn>



(희망저축계좌Ⅰ) 총 근로(사업)소득이 기준 중위소득 40%의 60% 이상인 생계의료급여 수급 가구를 대상으로 합니다.
(희망저축계좌Ⅱ) 가구 전체의 소득인정액이 기준 중위소득 50% 이하인 주거교육급여 수급 가구 및 차상위 가구를 대상으로 합니다.

</tgtrDtlCn><slctCritCn>



희망저축계좌Ⅰ의 선정기준은 다음과 같습니다. 

(생계의료 수급가구) 소득인정액이 기준중위소득 40% 이하인 가구 중
(근로활동) 가구원 중 일하는 사람이 있어야 하며
(소득기준) 신청 당시가구 전체의 총 근로사업소득(보장기관 확인 소득 제외)이 기준 중위소득 40%의 60% 이상인 가구

희망저축계좌Ⅱ의 선정기준은 다음과 같습니다. 

(소득기준) 가구 전체의 소득인정액이 기준 중위소득 50%이하인 주거교육급여 수급 가구 및 기타 차상위 계층 가구
(근로기준) 현재 근로활동 중이며 근로사업소득이 있는 가구


</slctCritCn><alwServCn>



희망저축계좌Ⅰ은 본인 저축액 월 10만원 이상 저축 시(전월 전월 23일~현월 22일 입금마감일 이전)정부지원금을 30만원을 매칭하여 지원합니다.
※ 탈수급시 지원금 전액 지급※ 정책대상별 추가지원금(탈수급장려급, 내일키움장려금, 내일키움수익금 등) 추가 지급 가능
희망저축계좌 Ⅱ는본인 저축액 월 10만원* 이상 저축시(전월 23일~현월 22일 입금마감일 이전) 정부지원금 10만원을 매칭하여 지원합니다.
* 정해진 교육(10시간) 이수 및 자금사용계획서 제출시 전액 지급 * 정책대상별 추가지원금(내일키움장려금, 내일키움수익금 등) 추가 지급 가능
2025년 가입자부터 근로소득장려금 연차별 차등지원 적용(1년차 월 10만원  2년차 월 20만원  3년차 월 30만원)

</alwServCn><crtrYr>2026</crtrYr><rprsCtadr>129</rprsCtadr><wlfareInfoOutlCn>희망저축계좌를 통해 일하는 생계·의료·주거·교육급여 수급가구 및 차상위계층이 자활에 필요한 자산을 형성할 수 있도록 지원합니다.</wlfareInfoOutlCn><sprtCycNm>월</sprtCycNm><srvPvsnNm>현금지급</srvPvsnNm><trgterIndvdlArray>저소득</trgterIndvdlArray><intrsThemaArray>생활지원, 서민금융</intrsThemaArray><applmetList><servSeCode>070</servSeCode><servSeDetailLink>거주지 읍/면/동 주민센터, 읍면동 주민센터에서 ‘서비스 신청’</servSeDetailLink><servSeDetailNm>신청기관연락처목록</servSeDetailNm></applmetList><applmetList><servSeCode>070</servSeCode><servSeDetailLink>거주지 읍/면/동 주민센터, 복지로(www.bokjiro.go.kr) 에서 ‘서비스 신청’</servSeDetailLink><servSeDetailNm>신청기관연락처목록</servSeDetailNm></applmetList><applmetList><servSeCode>070</servSeCode><servSeDetailLink>담당 시/군/구청 또는 시군구에서 조사 및 심사</servSeDetailLink><servSeDetailNm>조사기관연락처목록</servSeDetailNm></applmetList><applmetList><servSeCode>070</servSeCode><servSeDetailLink>담당 시/군/구청 또는 시군구에서 보장 결정</servSeDetailLink><servSeDetailNm>결정기관연락처목록 </servSeDetailNm></applmetList><applmetList><servSeCode>070</servSeCode><servSeDetailLink>이의가 있을 경우, 담당 시/군/구청 또는 시군구에 이의 신청 접수</servSeDetailLink><servSeDetailNm>이의신청접수기관연락처목록 </servSeDetailNm></applmetList><applmetList><servSeCode>070</servSeCode><servSeDetailLink>담당 시/군/구청 또는 한국자활복지개발원에서 대상자에게 서비스 제공</servSeDetailLink><servSeDetailNm>지급기관연락처목록 </servSeDetailNm></applmetList><applmetList><servSeCode>070</servSeCode><servSeDetailLink>담당 시/군/구청 또는 시군구에서 서비스 제공 이후 대상자의 상황 관리</servSeDetailLink><servSeDetailNm>사후관리기관목록</servSeDetailNm></applmetList><inqplCtadrList><servSeCode>010</servSeCode><servSeDetailLink>1522-3690</servSeDetailLink><servSeDetailNm>자산형성지원 콜센터</servSeDetailNm></inqplCtadrList><inqplCtadrList><servSeCode>010</servSeCode><servSeDetailLink>129</servSeDetailLink><servSeDetailNm>보건복지상담센터</servSeDetailNm></inqplCtadrList><inqplHmpgReldList><servSeCode>020</servSeCode><servSeDetailLink>https://hope.welfareinfo.or.kr</servSeDetailLink><servSeDetailNm>자산형성포털</servSeDetailNm></inqplHmpgReldList><inqplHmpgReldList><servSeCode>020</servSeCode><servSeDetailLink>http://www.129.go.kr</servSeDetailLink><servSeDetailNm>보건복지상담센터</servSeDetailNm></inqplHmpgReldList><basfrmList><servSeCode>040</servSeCode><servSeDetailLink>https://bokjiro.go.kr/ssis-tbu/CmmFileUtil/getDownload.do?atcflId=20260407TTWAT1353090010194108&amp;atcflSn=1</servSeDetailLink><servSeDetailNm>2026년_자활사업안내(II)_자산형성지원통장사업_안내.pdf</servSeDetailNm></basfrmList><baslawList><servSeCode>030</servSeCode><servSeDetailNm>국민기초생활 보장법 시행령</servSeDetailNm></baslawList><baslawList><servSeCode>030</servSeCode><servSeDetailNm>국민기초생활 보장법</servSeDetailNm></baslawList><resultCode>0</resultCode><resultMessage>SUCCESS</resultMessage></wantedDtl>